Workbook

Sheet Summary
A1: PhotoMe — Year 1 Financial Summary
A2: Single-university pilot launch. Conservative base case with realistic adoption assumptions.
A4: HEADLINE NUMBERS
A5: Total Revenue (Year 1) | B5: ='Monthly P&L'!O16 -> 6179.16 | C5: From Pro + Business subscriptions
A6: Total Costs (Year 1) | B6: ='Monthly P&L'!O27 -> 15454.074 | C6: Operating costs only — no founder salaries
A7: Net Position (Year 1) | B7: ='Monthly P&L'!O30 -> -9274.9142 | C7: Investment needed to reach Month 12
A8: Free users by Month 12 | B8: ='Monthly P&L'!N8 -> 5000 | C8: 20% of student body
A9: Pro subscribers by Month 12 | B9: ='Monthly P&L'!N9 -> 340 | C9: Recurring revenue base
A10: Monthly run-rate by Month 12 | B10: ='Monthly P&L'!N16 -> 1096.55 | C10: Trajectory entering Year 2
A13: WHERE THE MONEY GOES
A14: Cost line | B14: Year 1 total | C14: % of total
A15: Cloud hosting & storage | B15: ='Monthly P&L'!O19 -> 163.566 | C15: =B15/'Monthly P&L'!O27 -> 0.010584005
A16: App store + developer fees | B16: ='Monthly P&L'!O20 -> 204 | C16: =B16/'Monthly P&L'!O27 -> 0.013200402
A17: Marketing & paid social | B17: ='Monthly P&L'!O21 -> 6150 | C17: =B17/'Monthly P&L'!O27 -> 0.39795331
A18: Campus ambassadors | B18: ='Monthly P&L'!O22 -> 5300 | C18: =B18/'Monthly P&L'!O27 -> 0.34295163
A19: University society partnerships | B19: ='Monthly P&L'!O23 -> 1550 | C19: =B19/'Monthly P&L'!O27 -> 0.10029718
A20: Payment processing fees | B20: ='Monthly P&L'!O24 -> 86.50824 | C20: =B20/'Monthly P&L'!O27 -> 0.0055977627
A21: Legal, accounting & admin | B21: ='Monthly P&L'!O25 -> 1700 | C21: =B21/'Monthly P&L'!O27 -> 0.11000335
A22: Insurance & misc | B22: ='Monthly P&L'!O26 -> 300 | C22: =B22/'Monthly P&L'!O27 -> 0.019412357
A23: TOTAL | B23: =SUM(B15:B22) -> 15454.074 | C23: =SUM(C15:C22) -> 1
A25: KEY NOTES
A26: • Founder team unpaid in Year 1 — no salary line included. Adding two £18k/yr founder salaries would push Year 1 cost by ~£36k.
A27: • Pro conversion modelled at ~7% of free users (industry benchmark for freemium). User-research intent of 67% typically converts at 1/10th of stated rate.
A28: • Marketing peaks in September (Freshers) and January (Refreshers). Ambassador programme runs term-time only.
A29: • Phase 2 commercial launch (photographers, venues, multi-uni rollout) begins Year 2 — not modelled here.
A30: • Funding requirement: ~£12-15k pre-seed covers Year 1 operating loss and provides runway through Freshers 2027.

Sheet Assumptions
A1: PhotoMe — Year 1 Assumptions
A2: Pilot launch: single UK university (~25,000 students). Realistic, conservative base case.
A4: PRICING
A5: Pro tier monthly price | B5: 2.99 | C5: £/user/month
A6: Business tier monthly price | B6: 15.99 | C6: £/organiser/month
A7: Payment processing rate | B7: 0.014 | C7: Stripe 1.4% + 20p — fee modelled in monthly P&L
A8: Payment processing fixed fee | B8: 0.2 | C8: £ per transaction
A10: ADOPTION DRIVERS
A11: Target university student population | B11: 25000 | C11: Mid-sized UK university
A12: Target free-tier reach by Month 12 | B12: 5000 | C12: 20% of student body
A13: Pro conversion rate (realistic) | B13: 0.068 | C13: Industry freemium benchmark 2–8%; user-research intent was 67% but real conversion typically 1/10th of stated intent
A14: Business tier — organisers by Month 12 | B14: 5 | C14: Society/event partnerships
A15: Monthly Pro churn | B15: 0.05 | C15: 5% monthly churn on Pro tier
A17: COST DRIVERS
A18: Cloud hosting baseline | B18: 80 | C18: £/month — AWS/Firebase + storage, scales with users
A19: Hosting per 1,000 active users | B19: 60 | C19: Marginal cost per 1k MAU (storage + bandwidth)
A20: Apple Developer Programme | B20: 99 | C20: £99/year
A21: Google Play Developer | B21: 25 | C21: £25 one-off
A22: Domain + SSL + email | B22: 80 | C22: £/year
A23: Campus ambassador stipend | B23: 100 | C23: £/ambassador/month — 6 ambassadors at peak
A24: Society partnership fees | B24: 150 | C24: £/event society/term — Freshers, sports, balls
A25: Legal / accounting / admin | B25: 150 | C25: £/month average
A26: Insurance + misc compliance | B26: 40 | C26: £/month
A29: LEGEND
A30: Blue text = input / assumption (change to flex the model)
A31: Black text = formula / calculation

Sheet Monthly P&L
A1: PhotoMe — Year 1 Monthly P&L
A2: Single-university pilot. All values £. Blue = input, black = formula.
B4: Driver | C4: Jun 26 | D4: Jul 26 | E4: Aug 26 | F4: Sep 26 | G4: Oct 26 | H4: Nov 26 | I4: Dec 26 | J4: Jan 27 | K4: Feb 27 | L4: Mar 27 | M4: Apr 27 | N4: May 27 | O4: Year 1 Total
B5: Phase | C5: Pre-launch | D5: Beta | E5: Pre-Freshers | F5: Freshers Launch | G5: Growth | H5: Steady | I5: Holiday | J5: Refreshers | K5: Steady | L5: Event Season | M5: Ball Season | N5: Year-End Peak
A7: USERS
B8: Free-tier users (cumulative) | C8: 0 | D8: 50 | E8: 200 | F8: 1500 | G8: 2500 | H8: 3200 | I8: 3300 | J8: 3700 | K8: 4000 | L8: 4400 | M8: 4700 | N8: 5000 | O8: =SUM(C8:N8) -> 32550
B9: Pro subscribers (cumulative) | C9: 0 | D9: 0 | E9: 5 | F9: 60 | G9: 130 | H9: 180 | I9: 190 | J9: 220 | K9: 250 | L9: 280 | M9: 310 | N9: 340 | O9: =SUM(C9:N9) -> 1965
B10: Business subscribers (cumulative) | C10: 0 | D10: 0 | E10: 0 | F10: 0 | G10: 1 | H10: 1 | I10: 1 | J10: 2 | K10: 2 | L10: 3 | M10: 4 | N10: 5 | O10: =SUM(C10:N10) -> 19
B11: Pro conversion % | C11: =IF(C8=0,0,C9/C8) -> 0 | D11: =IF(D8=0,0,D9/D8) -> 0 | E11: =IF(E8=0,0,E9/E8) -> 0.025 | F11: =IF(F8=0,0,F9/F8) -> 0.04 | G11: =IF(G8=0,0,G9/G8) -> 0.052 | H11: =IF(H8=0,0,H9/H8) -> 0.05625 | I11: =IF(I8=0,0,I9/I8) -> 0.057575758 | J11: =IF(J8=0,0,J9/J8) -> 0.059459459 | ... N11: =IF(N8=0,0,N9/N8) -> 0.068 | O11: =IFERROR(N9/N8,0) -> 0.068
A13: REVENUE
B14: Pro subscription revenue | C14: =C9*Assumptions!$B$5 -> 0 | D14: =D9*Assumptions!$B$5 -> 0 | E14: =E9*Assumptions!$B$5 -> 14.95 | F14: =F9*Assumptions!$B$5 -> 179.4 | G14: =G9*Assumptions!$B$5 -> 388.7 | H14: =H9*Assumptions!$B$5 -> 538.2 | I14: =I9*Assumptions!$B$5 -> 568.1 | J14: =J9*Assumptions!$B$5 -> 657.8 | ... N14: =N9*Assumptions!$B$5 -> 1016.6 | O14: =SUM(C14:N14) -> 5875.35
B15: Business subscription revenue | C15: =C10*Assumptions!$B$6 -> 0 | D15: =D10*Assumptions!$B$6 -> 0 | E15: =E10*Assumptions!$B$6 -> 0 | F15: =F10*Assumptions!$B$6 -> 0 | G15: =G10*Assumptions!$B$6 -> 15.99 | H15: =H10*Assumptions!$B$6 -> 15.99 | I15: =I10*Assumptions!$B$6 -> 15.99 | J15: =J10*Assumptions!$B$6 -> 31.98 | ... N15: =N10*Assumptions!$B$6 -> 79.95 | O15: =SUM(C15:N15) -> 303.81
B16: Total Revenue | C16: =SUM(C14:C15) -> 0 | D16: =SUM(D14:D15) -> 0 | E16: =SUM(E14:E15) -> 14.95 | F16: =SUM(F14:F15) -> 179.4 | G16: =SUM(G14:G15) -> 404.69 | H16: =SUM(H14:H15) -> 554.19 | I16: =SUM(I14:I15) -> 584.09 | J16: =SUM(J14:J15) -> 689.78 | ... N16: =SUM(N14:N15) -> 1096.55 | O16: =SUM(C16:N16) -> 6179.16
A18: OPERATING COSTS
B19: Cloud hosting & storage | C19: =Assumptions!$B$13+(C8/1000)*Assumptions!$B$14 -> 0.068 | D19: =Assumptions!$B$13+(D8/1000)*Assumptions!$B$14 -> 0.318 | E19: =Assumptions!$B$13+(E8/1000)*Assumptions!$B$14 -> 1.068 | F19: =Assumptions!$B$13+(F8/1000)*Assumptions!$B$14 -> 7.568 | G19: =Assumptions!$B$13+(G8/1000)*Assumptions!$B$14 -> 12.568 | H19: =Assumptions!$B$13+(H8/1000)*Assumptions!$B$14 -> 16.068 | I19: =Assumptions!$B$13+(I8/1000)*Assumptions!$B$14 -> 16.568 | J19: =Assumptions!$B$13+(J8/1000)*Assumptions!$B$14 -> 18.568 | ... N19: =Assumptions!$B$13+(N8/1000)*Assumptions!$B$14 -> 25.068 | O19: =SUM(C19:N19) -> 163.566
B20: App store + developer fees | C20: 204 | D20: 0 | E20: 0 | F20: 0 | G20: 0 | H20: 0 | I20: 0 | J20: 0 | K20: 0 | L20: 0 | M20: 0 | N20: 0 | O20: =SUM(C20:N20) -> 204
B21: Marketing & paid social ads | C21: 50 | D21: 100 | E21: 400 | F21: 1500 | G21: 800 | H21: 500 | I21: 200 | J21: 700 | K21: 400 | L21: 500 | M21: 600 | N21: 400 | O21: =SUM(C21:N21) -> 6150
B22: Campus ambassadors | C22: 0 | D22: 0 | E22: 200 | F22: 600 | G22: 600 | H22: 600 | I22: 400 | J22: 600 | K22: 600 | L22: 600 | M22: 600 | N22: 500 | O22: =SUM(C22:N22) -> 5300
B23: University society partnerships | C23: 0 | D23: 0 | E23: 150 | F23: 300 | G23: 200 | H23: 100 | I23: 0 | J23: 150 | K23: 100 | L23: 200 | M23: 200 | N23: 150 | O23: =SUM(C23:N23) -> 1550
B24: Payment processing fees | C24: =C16*Assumptions!$B$7 -> 0 | D24: =D16*Assumptions!$B$7 -> 0 | E24: =E16*Assumptions!$B$7 -> 0.2093 | F24: =F16*Assumptions!$B$7 -> 2.5116 | G24: =G16*Assumptions!$B$7 -> 5.66566 | H24: =H16*Assumptions!$B$7 -> 7.75866 | I24: =I16*Assumptions!$B$7 -> 8.17726 | J24: =J16*Assumptions!$B$7 -> 9.65692 | ... N24: =N16*Assumptions!$B$7 -> 15.3517 | O24: =SUM(C24:N24) -> 86.50824
B25: Legal, accounting & admin | C25: 200 | D25: 100 | E25: 100 | F25: 150 | G25: 150 | H25: 150 | I25: 100 | J25: 150 | K25: 150 | L25: 150 | M25: 150 | N25: 150 | O25: =SUM(C25:N25) -> 1700
B26: Insurance & misc | C26: =Assumptions!$B$21 -> 25 | D26: =Assumptions!$B$21 -> 25 | E26: =Assumptions!$B$21 -> 25 | F26: =Assumptions!$B$21 -> 25 | G26: =Assumptions!$B$21 -> 25 | H26: =Assumptions!$B$21 -> 25 | I26: =Assumptions!$B$21 -> 25 | J26: =Assumptions!$B$21 -> 25 | ... N26: =Assumptions!$B$21 -> 25 | O26: =SUM(C26:N26) -> 300
B27: Total Costs | C27: =SUM(C19:C26) -> 479.068 | D27: =SUM(D19:D26) -> 225.318 | E27: =SUM(E19:E26) -> 876.2773 | F27: =SUM(F19:F26) -> 2585.0796 | G27: =SUM(G19:G26) -> 1793.2337 | H27: =SUM(H19:H26) -> 1398.8267 | I27: =SUM(I19:I26) -> 749.74526 | J27: =SUM(J19:J26) -> 1653.2249 | ... N27: =SUM(N19:N26) -> 1265.4197 | O27: =SUM(C27:N27) -> 15454.074
A29: NET POSITION
B30: Net profit / (loss) | C30: =C16-C27 -> -479.068 | D30: =D16-D27 -> -225.318 | E30: =E16-E27 -> -861.3273 | F30: =F16-F27 -> -2405.6796 | G30: =G16-G27 -> -1388.5437 | H30: =H16-H27 -> -844.63666 | I30: =I16-I27 -> -165.65526 | J30: =J16-J27 -> -963.44492 | ... N30: =N16-N27 -> -168.8697 | O30: =SUM(C30:N30) -> -9274.9142
B31: Cumulative cash position | C31: =C30 -> -479.068 | D31: =C31+D30 -> -704.386 | E31: =D31+E30 -> -1565.7133 | F31: =E31+F30 -> -3971.3929 | G31: =F31+G30 -> -5359.9366 | H31: =G31+H30 -> -6204.5732 | I31: =H31+I30 -> -6370.2285 | J31: =I31+J30 -> -7333.6734 | K31: =J31+K30 -> -7860.1741 | ... N31: =M31+N30 -> -9274.9142 | O31: =N31 -> -9274.9142
